env_tools.py
env_tools-2.2.0.dist-info/DESCRIPTION.rst
env_tools-2.2.0.dist-info/METADATA
env_tools-2.2.0.dist-info/RECORD
env_tools-2.2.0.dist-info/WHEEL
env_tools-2.2.0.dist-info/metadata.json
env_tools-2.2.0.dist-info/top_level.txt
