Metadata-Version: 1.1
Name: env-tools
Version: 2.2.0
Summary: Tools for using .env files in Python
Home-page: https://github.com/beaugunderson/python-env-tools
Author: Beau Gunderson
Author-email: beau@beaugunderson.com
License: MIT
Keywords: .env env heroku procfile foreman
Platform: UNKNOWN
Classifier: Development Status :: 5 - Production/Stable
Classifier: Intended Audience :: Developers
Classifier: License :: OSI Approved :: MIT License
Classifier: Operating System :: POSIX
Classifier: Operating System :: Microsoft :: Windows
Classifier: Operating System :: MacOS :: MacOS X
Classifier: Topic :: Software Development :: Libraries
Classifier: Topic :: Utilities
Classifier: Programming Language :: Python :: 2
Classifier: Programming Language :: Python :: 2.7
Classifier: Programming Language :: Python :: 3
Classifier: Programming Language :: Python :: 3.4
